CHANGES.txt
README.txt
buildout.cfg
setup.py
src/z3c/__init__.py
src/z3c.davapp.zopelocking.egg-info/PKG-INFO
src/z3c.davapp.zopelocking.egg-info/SOURCES.txt
src/z3c.davapp.zopelocking.egg-info/dependency_links.txt
src/z3c.davapp.zopelocking.egg-info/namespace_packages.txt
src/z3c.davapp.zopelocking.egg-info/not-zip-safe
src/z3c.davapp.zopelocking.egg-info/requires.txt
src/z3c.davapp.zopelocking.egg-info/top_level.txt
src/z3c/davapp/__init__.py
src/z3c/davapp/zopelocking/__init__.py
src/z3c/davapp/zopelocking/configure.zcml
src/z3c/davapp/zopelocking/ftesting.zcml
src/z3c/davapp/zopelocking/ftests.py
src/z3c/davapp/zopelocking/indirecttokens.py
src/z3c/davapp/zopelocking/interfaces.py
src/z3c/davapp/zopelocking/manager.py
src/z3c/davapp/zopelocking/properties.py
src/z3c/davapp/zopelocking/tests.py