Metadata-Version: 1.0
Name: z3c.davapp.zopelocking
Version: 1.0b1
Summary: WebDAV locking support using zope.locking
Home-page: http://launchpad.net/z3c.dav
Author: Michael Kerrin
Author-email: michael.kerrin@openapp.ie
License: ZPL
Platform: UNKNOWN
Classifier: Environment :: Web Environment
Classifier: Intended Audience :: Developers
Classifier: License :: OSI Approved :: Zope Public License
Classifier: Programming Language :: Python
Classifier: Framework :: Zope3
